README.rst
setup.py
wdapi/__init__.py
wdapi/main.py
wdapi.egg-info/PKG-INFO
wdapi.egg-info/SOURCES.txt
wdapi.egg-info/dependency_links.txt
wdapi.egg-info/requires.txt
wdapi.egg-info/top_level.txt