Metadata-Version: 1.1
Name: wdapi
Version: 1.2.0
Summary: A simple API to parse constraints of properties on Wikidata for wmflabs.
Home-page: https://github.com/legoktm/wdapi
Author: Kunal Mehta
Author-email: legoktm@gmail.com
License: Public domain
Platform: UNKNOWN
Classifier: Programming Language :: Python
Classifier: Programming Language :: Python :: 2
Classifier: Intended Audience :: Developers
Classifier: Operating System :: OS Independent
